no2ml/__init__.py
no2ml/main.py
no2ml-0.0.1.dist-info/LICENSE
no2ml-0.0.1.dist-info/METADATA
no2ml-0.0.1.dist-info/WHEEL
no2ml-0.0.1.dist-info/entry_points.txt
no2ml-0.0.1.dist-info/top_level.txt
no2ml-0.0.1.dist-info/RECORD
