Metadata-Version: 2.1
Name: no2ml
Version: 0.0.1
Summary: (Early Dev)Convert Notion Export HTML To Latex
Home-page: https://github.com/Lu-MPI/NotionHTMLToLatex
Author: Lu
Author-email: lu2github@gmail.com
License: UNKNOWN
Platform: UNKNOWN
Classifier: Programming Language :: Python :: 3
Classifier: License :: OSI Approved :: MIT License
Classifier: Operating System :: OS Independent
License-File: LICENSE
